CMakeLists.txt
LICENSE
MANIFEST.in
Makefile
README.md
pyproject.toml
requirements-dev.txt
requirements.txt
setup.cfg
setup.py
pychadwick/__init__.py
pychadwick/book.py
pychadwick/box.py
pychadwick/chadwick.py
pychadwick/experiments.py
pychadwick/game.py
pychadwick/gameiter.py
pychadwick/league.py
pychadwick/parse.py
pychadwick/roster.py
pychadwick/utils.py
pychadwick.egg-info/PKG-INFO
pychadwick.egg-info/SOURCES.txt
pychadwick.egg-info/dependency_links.txt
pychadwick.egg-info/entry_points.txt
pychadwick.egg-info/requires.txt
pychadwick.egg-info/top_level.txt
pychadwick/cli/__init__.py
pychadwick/cli/pycwevent.py
pychadwick/libutils/__init__.py
pychadwick/libutils/cwlib.py
src/Makefile
src/pychadwicklib/LICENSE
src/pychadwicklib/Makefile
src/pychadwicklib/cwlib/book.c
src/pychadwicklib/cwlib/book.h
src/pychadwicklib/cwlib/box.c
src/pychadwicklib/cwlib/box.h
src/pychadwicklib/cwlib/chadwick.h
src/pychadwicklib/cwlib/file.c
src/pychadwicklib/cwlib/file.h
src/pychadwicklib/cwlib/game.c
src/pychadwicklib/cwlib/game.h
src/pychadwicklib/cwlib/gameiter.c
src/pychadwicklib/cwlib/gameiter.h
src/pychadwicklib/cwlib/league.c
src/pychadwicklib/cwlib/league.h
src/pychadwicklib/cwlib/lint.c
src/pychadwicklib/cwlib/parse.c
src/pychadwicklib/cwlib/parse.h
src/pychadwicklib/cwlib/roster.c
src/pychadwicklib/cwlib/roster.h
src/pychadwicklib/cwtools/cwbox.c
src/pychadwicklib/cwtools/cwboxsml.c
src/pychadwicklib/cwtools/cwboxxml.c
src/pychadwicklib/cwtools/cwcomment.c
src/pychadwicklib/cwtools/cwdaily.c
src/pychadwicklib/cwtools/cwevent.c
src/pychadwicklib/cwtools/cwgame.c
src/pychadwicklib/cwtools/cwsub.c
src/pychadwicklib/cwtools/cwtools.c
src/pychadwicklib/cwtools/xmlwrite.c
src/pychadwicklib/cwtools/xmlwrite.h