Metadata-Version: 2.1
Name: pychadwick
Version: 0.6.1
Summary: Python bindings to the Chadwick library
Home-page: https://github.com/bdilday/pychadwick
Author: Ben Dilday
Author-email: ben.dilday.phd@gmail.com
License: UNKNOWN
Platform: UNKNOWN
Classifier: Programming Language :: Python :: 3
Classifier: Programming Language :: C
Classifier: License :: OSI Approved :: GNU General Public License v2 (GPLv2)
Classifier: Operating System :: OS Independent
License-File: LICENSE
